mediainfo_generator/__init__.py
mediainfo_generator/logging.yaml
mediainfo_generator/utils/cli_args.py
mediainfo_generator/utils/logging_utils.py
mediainfo_generator/utils/media_utils.py
mediainfo_generator/utils/settings_utils_v1.py
mediainfo_generator-0.1.1.dist-info/METADATA
mediainfo_generator-0.1.1.dist-info/WHEEL
mediainfo_generator-0.1.1.dist-info/entry_points.txt
mediainfo_generator-0.1.1.dist-info/RECORD
