Metadata-Version: 2.1
Name: mediainfo-generator
Version: 0.1.1
Summary: 
Home-page: https://github.com/ravensorb/mediainfo-generator
Author: Shawn Anderson
Author-email: sanderson@eye-catcher.com
Requires-Python: >=3.10,<4.0
Classifier: Programming Language :: Python :: 3
Classifier: Programming Language :: Python :: 3.10
Classifier: Programming Language :: Python :: 3.11
Classifier: Topic :: Utilities
Requires-Dist: coloredlogs (>=15.0.1,<16.0.0)
Requires-Dist: confuse (>=2.0.1,<3.0.0)
Requires-Dist: importlib-resources (>=5.12.0,<6.0.0)
Requires-Dist: readchar (>=4.0.5,<5.0.0)
Requires-Dist: ruamel-yaml (>=0.17.21,<0.18.0)
Project-URL: Repository, https://github.com/ravensorb/media-info-generator
